.DS_Store
throws/__init__.py
throws/throws.py
throws/throws_test.py
throws-1.0.6.dist-info/LICENSE
throws-1.0.6.dist-info/METADATA
throws-1.0.6.dist-info/WHEEL
throws-1.0.6.dist-info/top_level.txt
throws-1.0.6.dist-info/RECORD
