Metadata-Version: 2.1
Name: throws
Version: 1.0.6
Summary: Python implementation of the @throws(...) function decorator provided by Kotlin!
Home-page: https://github.com/thahnen/throws
Author: Tobias Hahnen
Author-email: hahnen.tobi@gmail.com
License: MIT License
Platform: UNKNOWN
Classifier: Programming Language :: Python :: 3
Classifier: License :: OSI Approved :: MIT License
Classifier: Intended Audience :: Developers
Classifier: Topic :: Software Development
Classifier: Natural Language :: English
Classifier: Operating System :: OS Independent
Classifier: Development Status :: 5 - Production/Stable
License-File: LICENSE
